useful_funcs/__init__.py
useful_funcs/useful_calendar.py
useful_funcs/useful_calendar_functions.py
useful_funcs/useful_closest.py
useful_funcs/useful_colors.py
useful_funcs/useful_datetime.py
useful_funcs/useful_datetime_functions.py
useful_funcs/useful_file_rename.py
useful_funcs/useful_interpol.py
useful_funcs/useful_isolated_points.py
useful_funcs/useful_stats_functions.py
useful_funcs/useful_tdf.py
useful_funcs/useful_thermodynamics.py
useful_funcs-0.2.2.dist-info/LICENSE
useful_funcs-0.2.2.dist-info/METADATA
useful_funcs-0.2.2.dist-info/WHEEL
useful_funcs-0.2.2.dist-info/top_level.txt
useful_funcs-0.2.2.dist-info/RECORD
