Metadata-Version: 2.1
Name: useful_funcs
Version: 0.2.2
Summary: Useful Functions
Author: SuryaSudh
Author-email: <suryasudhakar7@outlook.com>
Keywords: python,useful,useful functions,unit conversion,date conversion,calendar functions
Classifier: Development Status :: 1 - Planning
Classifier: Intended Audience :: Developers
Classifier: Programming Language :: Python :: 3
Classifier: Operating System :: Unix
Classifier: Operating System :: MacOS :: MacOS X
Classifier: Operating System :: Microsoft :: Windows
License-File: LICENSE
Requires-Dist: datetime
Requires-Dist: numpy
